torch_tda/__init__.py
torch_tda/nn/__init__.py
torch_tda/nn/diagram_dist.py
torch_tda/nn/levelset.py
torch_tda/nn/poly_feat.py
torch_tda/nn/rips.py
torch_tda/nn/functional/__init__.py
torch_tda/nn/functional/bottleneck.py
torch_tda/nn/functional/rips.py
torch_tda/nn/functional/sublevel.py
torch_tda/nn/functional/util.py
torch_tda/nn/functional/wasserstein.py
torch_tda-0.0.1.dist-info/LICENSE
torch_tda-0.0.1.dist-info/METADATA
torch_tda-0.0.1.dist-info/WHEEL
torch_tda-0.0.1.dist-info/top_level.txt
torch_tda-0.0.1.dist-info/RECORD
