Metadata-Version: 2.1
Name: torch-tda
Version: 0.0.1
Summary: Automatic differentiation for topological data analysis
Home-page: https://github.com/CompTop/torch-tda
Author: Brad Nelson, Yuan Luo
Author-email: bradnelson@uchicago.edu, yuanluo@uchicago.edu
License: MIT
Project-URL: Documentation, https://torch-tda.readthedocs.io/en/latest/
Keywords: topological data analysis,automatic differentiation,persistent homology
Platform: UNKNOWN
Classifier: Development Status :: 3 - Alpha
Classifier: Intended Audience :: Science/Research
Classifier: Intended Audience :: Education
Classifier: Topic :: Scientific/Engineering :: Information Analysis
Classifier: Topic :: Scientific/Engineering :: Mathematics
Classifier: License :: OSI Approved :: MIT License
Classifier: Operating System :: POSIX :: Linux
Classifier: Programming Language :: Python :: 3
Classifier: Programming Language :: Python :: 3.7
Requires-Python: >=3.7
License-File: LICENSE
Requires-Dist: numpy
Requires-Dist: bats-tda
Requires-Dist: persim (>=0.3.1)
Requires-Dist: scipy
